worldbankpy/__init__.py
worldbankpy/const.py
worldbankpy/main.py
worldbankpy/utils.py
worldbankpy-0.1.dist-info/METADATA
worldbankpy-0.1.dist-info/WHEEL
worldbankpy-0.1.dist-info/top_level.txt
worldbankpy-0.1.dist-info/RECORD
