Metadata-Version: 2.1
Name: worldbankpy
Version: 0.1
Summary: Fetches macroeconomic data from World Bank.
Home-page: https://github.com/nndjoli/world-bank-data-fetcher
Author: nndjoli
License: UNKNOWN
Platform: UNKNOWN
Requires: requests
Requires: pandas
Requires: datetime
